tb_forms/__init__.py
tb_forms/fields.py
tb_forms/form.py
tb_forms/tb_fsm.py
tb_forms/tbf_types.py
tb_forms/validators.py
TBForms-0.9.16.dist-info/LICENSE
TBForms-0.9.16.dist-info/METADATA
TBForms-0.9.16.dist-info/WHEEL
TBForms-0.9.16.dist-info/top_level.txt
TBForms-0.9.16.dist-info/RECORD
