Metadata-Version: 2.1
Name: TBForms
Version: 0.9.16
Summary: Small extension for pyTelegramBotAPI library for building interactive forms in Telegram bots.
Home-page: https://github.com/wathipol/TBForms
Author: watdev
Author-email: v.liubachevskyi@gmail.com
Classifier: Programming Language :: Python :: 3.8
Classifier: License :: OSI Approved :: MIT License
Classifier: Operating System :: OS Independent
Requires-Python: >=3.7
License-File: LICENSE
Requires-Dist: pyTelegramBotAPI
Requires-Dist: dill
